{
    "additions.midnightconfig.DayOfMind": "DayOfMind",
    "additions.midnightconfig.DetailedLogging": "Gedetailleerde Aantekening",
    "additions.midnightconfig.DetailedLogging.tooltip": "Aktiveer gedetailleerde aantekening van hierdie mod, soos die aflaai van vertalings. Jy wil dit waarskynlik nie aktiveer nie weens die log-spam.",
    "additions.midnightconfig.EnabledBlockVariants": "Aktiveer Blokvariante",
    "additions.midnightconfig.EnabledBlockVariants.tooltip": "Aktiveer die vermoë om meer blokvariante (trappe, blaaie) te maak",
    "additions.midnightconfig.EnabledInstruments": "Aktiveer Instrumente",
    "additions.midnightconfig.EnabledInstruments.tooltip": "Aktiveer die vermoë om instrumente te maak",
    "additions.midnightconfig.EnabledLantern": "Aktiveer Lanterns",
    "additions.midnightconfig.EnabledLantern.tooltip": "Aktiveer die vermoë om meer lanterns te maak",
    "additions.midnightconfig.EnabledRedstoneLantern": "Aktiveer Redstone Lanterns",
    "additions.midnightconfig.EnabledRedstoneLantern.tooltip": "Aktiveer die vermoë om redstone-lanterns te maak",
    "additions.midnightconfig.EnabledShovelMixin": "Aktiveer Graafpad Wissel",
    "additions.midnightconfig.EnabledShovelMixin.tooltip": "Laat jou toe om met 'n graaf tussen Grasblok en Grondpad te wissel",
    "additions.midnightconfig.EnabledTranslation": "Aktiveer Vertalings",
    "additions.midnightconfig.EnabledTranslation.tooltip": "Aktiveer die outomatiese aflaai van vertalings",
    "additions.midnightconfig.EnabledTrapdoor": "Aktiveer Valdeure",
    "additions.midnightconfig.EnabledTrapdoor.tooltip": "Aktiveer die vermoë om meer valdeure te maak",
    "additions.midnightconfig.TranslationCounter": "Starts for translation download",
    "additions.midnightconfig.TranslationCounter.tooltip": "enter the number of game starts at which you'd like to pause translation updates.",
    "additions.midnightconfig.TranslationUrl": "Vertaalbron",
    "additions.midnightconfig.TranslationUrl.tooltip": "Kies die bron van die vertalings",
    "additions.midnightconfig.TranslationUrlCustom": "Gepasmaakte Vertaalbron",
    "additions.midnightconfig.TranslationUrlCustom.tooltip": "Voer die URL van die gepasmaakte vertaalbron in",
    "additions.midnightconfig.aboutDayOfMind": "DayOfMind is 'n mod wat nuwe blokke, resepte en kenmerke byvoeg. Met unieke lanterns, uitgebreide blokvariasies en slim kenmerke soos om gras- en grondpaaie met 'n graaf te wissel, bied DayOfMind opwindende moontlikhede vir jou avonture.",
    "additions.midnightconfig.category.about": "Oor DayOfMind",
    "additions.midnightconfig.category.features": "Kenmerke",
    "additions.midnightconfig.enum.TranslationVersion.CROWDIN": "Crowdin",
    "additions.midnightconfig.enum.TranslationVersion.CUSTOM": "Gepasmaak",
    "additions.midnightconfig.enum.TranslationVersion.OXFATECH": "OxFaTech",
    "additions.midnightconfig.features": "Die instellings wat hier gelys word, is ten volle ontwikkel en kan veilig gebruik word.",
    "additions.midnightconfig.title": "DayOfMind-konfigurasie",
    "item.additions.big_diamond_shovel": "Groot Diamantgraaf",
    "item.additions.big_gold_shovel": "Groot Goue Graaf",
    "item.additions.big_iron_shovel": "Groot Ystergraaf",
    "item.additions.big_netherite_shovel": "Groot Netherietgraaf",
    "item.additions.big_stone_shovel": "Groot Klipgraaf",
    "item.additions.big_wood_shovel": "Groot Houtgraaf",
    "item.additions.diamond_hammer": "Diamanthamer",
    "item.additions.gold_hammer": "Goue Hamer",
    "item.additions.iron_hammer": "Ysterhamer",
    "item.additions.netherite_hammer": "Netheriethamer",
    "item.additions.stone_hammer": "Kliphamer",
    "item.additions.wood_hammer": "Houthamer",
    "item.minecraft.amethyst_big_lantern": "Groot Ametislantern",
    "item.minecraft.amethyst_big_redstone_lantern": "Groot Ametis Redstone-lantern",
    "item.minecraft.amethyst_lantern": "Ametislantern",
    "item.minecraft.amethyst_redstone_lantern": "Ametis Redstone-lantern",
    "item.minecraft.amethyst_small_lantern": "Klein Ametislantern",
    "item.minecraft.amethyst_small_redstone_lantern": "Klein Ametis Redstone-lantern",
    "item.minecraft.amethyst_trapdoor": "Ametisvaldeur",
    "item.minecraft.andesite_trapdoor": "Andesietvaldeur",
    "item.minecraft.basalt_trapdoor": "Basaltvaldeur",
    "item.minecraft.blackstone_trapdoor": "Swartklipvaldeur",
    "item.minecraft.bricks_trapdoor": "Baksteenvaldeur",
    "item.minecraft.chiseled_deepslate_trapdoor": "Gekerfde Diepleivaldeur",
    "item.minecraft.chiseled_polished_blackstone_trapdoor": "Gekerfde Gepoleerde Swartklipvaldeur",
    "item.minecraft.chiseled_quartz_trapdoor": "Gekerfde Kwartsvaldeur",
    "item.minecraft.chiseled_red_sandstone_trapdoor": "Gekerfde Rooi Sandsteenvaldeur",
    "item.minecraft.chiseled_sandstone_trapdoor": "Gekerfde Sandsteenvaldeur",
    "item.minecraft.chiseled_stone_bricks_trapdoor": "Gekerfde Klipbaksteenvaldeur",
    "item.minecraft.chiseled_tuff_bricks_trapdoor": "Gekerfde Tufbaksteenvaldeur",
    "item.minecraft.chiseled_tuff_trapdoor": "Gekerfde Tufvaldeur",
    "item.minecraft.coarse_dirt_slab": "Growwe Grondblad",
    "item.minecraft.coarse_dirt_stairs": "Growwe Grondtrappe",
    "item.minecraft.cobbled_deepslate_trapdoor": "Keisteen Diepleivaldeur",
    "item.minecraft.cobblestone_trapdoor": "Keisteenvaldeur",
    "item.minecraft.copper_big_lantern": "Groot Koperlantern",
    "item.minecraft.copper_big_redstone_lantern": "Groot Koper Redstone-lantern",
    "item.minecraft.copper_lantern": "Koperlantern",
    "item.minecraft.copper_redstone_lantern": "Koper Redstone-lantern",
    "item.minecraft.copper_small_lantern": "Klein Koperlantern",
    "item.minecraft.copper_small_redstone_lantern": "Klein Koper Redstone-lantern",
    "item.minecraft.crying_obsidian_slab": "Huilende Obsidiaanblad",
    "item.minecraft.crying_obsidian_stairs": "Huilende Obsidiaantrap",
    "item.minecraft.dark_prismarine_trapdoor": "Donker Prismarienvaldeur",
    "item.minecraft.deepslate_bricks_trapdoor": "Diepleibaksteenvaldeur",
    "item.minecraft.deepslate_tiles_trapdoor": "Diepleiteëlvaldeur",
    "item.minecraft.deepslate_trapdoor": "Diepleivaldeur",
    "item.minecraft.diamond_big_lantern": "Groot Diamantlantern",
    "item.minecraft.diamond_big_redstone_lantern": "Groot Diamant Redstone-lantern",
    "item.minecraft.diamond_lantern": "Diamantlantern",
    "item.minecraft.diamond_redstone_lantern": "Diamant Redstone-lantern",
    "item.minecraft.diamond_slab": "Diamantblad",
    "item.minecraft.diamond_small_lantern": "Klein Diamantlantern",
    "item.minecraft.diamond_small_redstone_lantern": "Klein Diamant Redstone-lantern",
    "item.minecraft.diamond_stairs": "Diamanttrap",
    "item.minecraft.diamond_trapdoor": "Diamantvaldeur",
    "item.minecraft.diorite_trapdoor": "Diorietvaldeur",
    "item.minecraft.dirt_path_slab": "Grondpadblad",
    "item.minecraft.dirt_path_stairs": "Grondpadtrap",
    "item.minecraft.dirt_slab": "Grondblad",
    "item.minecraft.dirt_stairs": "Grondtrap",
    "item.minecraft.emerald_big_lantern": "Groot Smaraglantern",
    "item.minecraft.emerald_big_redstone_lantern": "Groot Smarag Redstone-lantern",
    "item.minecraft.emerald_lantern": "Smaraglantern",
    "item.minecraft.emerald_redstone_lantern": "Smarag Redstone-lantern",
    "item.minecraft.emerald_small_lantern": "Klein Smaraglantern",
    "item.minecraft.emerald_small_redstone_lantern": "Klein Smarag Redstone-lantern",
    "item.minecraft.emerald_trapdoor": "Smaragvaldeur",
    "item.minecraft.end_stone_bricks_trapdoor": "Eindklipbaksteenvaldeur",
    "item.minecraft.end_stone_trapdoor": "Eindklipvaldeur",
    "item.minecraft.gold_big_lantern": "Groot Gouelantarn",
    "item.minecraft.gold_big_redstone_lantern": "Groot Goue Redstone-lantern",
    "item.minecraft.gold_lantern": "Gouelantarn",
    "item.minecraft.gold_redstone_lantern": "Goue Redstone-lantern",
    "item.minecraft.gold_slab": "Goueblad",
    "item.minecraft.gold_small_lantern": "Klein Gouelantarn",
    "item.minecraft.gold_small_redstone_lantern": "Klein Goue Redstone-lantern",
    "item.minecraft.gold_stairs": "Gouetrap",
    "item.minecraft.gold_trapdoor": "Gouevaldeur",
    "item.minecraft.granite_trapdoor": "Granietvaldeur",
    "item.minecraft.grass_slab": "Grasblad",
    "item.minecraft.grass_stairs": "Grastrap",
    "item.minecraft.iron_big_lantern": "Groot Ysterlantern",
    "item.minecraft.iron_big_redstone_lantern": "Groot Yster Redstone-lantern",
    "item.minecraft.iron_redstone_lantern": "Yster Redstone-lantern",
    "item.minecraft.iron_slab": "Ysterblad",
    "item.minecraft.iron_small_lantern": "Klein Ysterlantern",
    "item.minecraft.iron_small_redstone_lantern": "Klein Yster Redstone-lantern",
    "item.minecraft.iron_stairs": "Ystertrap",
    "item.minecraft.magma_slab": "Magmablad",
    "item.minecraft.magma_stairs": "Magmatrap",
    "item.minecraft.moss_slab": "Mosblad",
    "item.minecraft.moss_stairs": "Mostrap",
    "item.minecraft.mossy_cobblestone_trapdoor": "Bemoste Keisteenvaldeur",
    "item.minecraft.mossy_stone_bricks_trapdoor": "Bemoste Klipbaksteenvaldeur",
    "item.minecraft.mud_bricks_trapdoor": "Modderbaksteenvaldeur",
    "item.minecraft.mud_slab": "Modderblad",
    "item.minecraft.mud_stairs": "Moddertrap",
    "item.minecraft.muddy_mangrove_roots_slab": "Modderige Mangrovewortelblad",
    "item.minecraft.muddy_mangrove_roots_stairs": "Modderige Mangroveworteltrap",
    "item.minecraft.mycelium_slab": "Miselliumblad",
    "item.minecraft.mycelium_stairs": "Miselliumtrap",
    "item.minecraft.nether_bricks_trapdoor": "Netherbaksteenvaldeur",
    "item.minecraft.netherite_big_lantern": "Groot Netherietlantern",
    "item.minecraft.netherite_big_redstone_lantern": "Groot Netheriet Redstone-lantern",
    "item.minecraft.netherite_lantern": "Netherietlantern",
    "item.minecraft.netherite_redstone_lantern": "Netheriet Redstone-lantern",
    "item.minecraft.netherite_small_lantern": "Klein Netherietlantern",
    "item.minecraft.netherite_small_redstone_lantern": "Klein Netheriet Redstone-lantern",
    "item.minecraft.netherite_trapdoor": "Netherietvaldeur",
    "item.minecraft.netherrack_trapdoor": "Netherrakvaldeur",
    "item.minecraft.obsidian_slab": "Obsidiaanblad",
    "item.minecraft.obsidian_stairs": "Obsidiaantrap",
    "item.minecraft.podzol_slab": "Podsolblad",
    "item.minecraft.podzol_stairs": "Podsoltrap",
    "item.minecraft.polished_andesite_trapdoor": "Gepoleerde Andesietvaldeur",
    "item.minecraft.polished_basalt_slab": "Gepoleerde Basaltblad",
    "item.minecraft.polished_basalt_stairs": "Gepoleerde Basalttrap",
    "item.minecraft.polished_basalt_trapdoor": "Gepoleerde Basaltvaldeur",
    "item.minecraft.polished_blackstone_bricks_trapdoor": "Gepoleerde Swartklipbaksteenvaldeur",
    "item.minecraft.polished_blackstone_trapdoor": "Gepoleerde Swartklipvaldeur",
    "item.minecraft.polished_deepslate_trapdoor": "Gepoleerde Diepleivaldeur",
    "item.minecraft.polished_diorite_trapdoor": "Gepoleerde Diorietvaldeur",
    "item.minecraft.polished_granite_trapdoor": "Gepoleerde Granietvaldeur",
    "item.minecraft.polished_tuff_trapdoor": "Gepoleerde Tufvaldeur",
    "item.minecraft.prismarine_bricks_trapdoor": "Prismarienbaksteenvaldeur",
    "item.minecraft.prismarine_trapdoor": "Prismarienvaldeur",
    "item.minecraft.purpur_trapdoor": "Purpurvaldeur",
    "item.minecraft.quartz_bricks_trapdoor": "Kwartsbaksteenvaldeur",
    "item.minecraft.quartz_trapdoor": "Kwartsvaldeur",
    "item.minecraft.red_nether_bricks_trapdoor": "Rooi Netherbaksteenvaldeur",
    "item.minecraft.red_sandstone_trapdoor": "Rooi Sandsteenvaldeur",
    "item.minecraft.redstone_chain": "Redstone-ketting",
    "item.minecraft.rooted_dirt_slab": "Bewortelde Grondblad",
    "item.minecraft.rooted_dirt_stairs": "Bewortelde Grondtrap",
    "item.minecraft.sandstone_trapdoor": "Sandsteenvaldeur",
    "item.minecraft.smooth_basalt_slab": "Gladde Basaltblad",
    "item.minecraft.smooth_basalt_stairs": "Gladde Basalttrap",
    "item.minecraft.smooth_basalt_trapdoor": "Gladde Basaltvaldeur",
    "item.minecraft.smooth_quartz_trapdoor": "Gladde Kwartsvaldeur",
    "item.minecraft.smooth_red_sandstone_trapdoor": "Gladde Rooi Sandsteenvaldeur",
    "item.minecraft.smooth_sandstone_trapdoor": "Gladde Sandsteenvaldeur",
    "item.minecraft.smooth_stone_trapdoor": "Gladde Klipvaldeur",
    "item.minecraft.stone_bricks_trapdoor": "Klipbaksteenvaldeur",
    "item.minecraft.stone_trapdoor": "Klipvaldeur",
    "item.minecraft.tuff_bricks_trapdoor": "Tufbaksteenvaldeur",
    "item.minecraft.tuff_trapdoor": "Tufvaldeur",
    "itemGroup.additions.blocks": "DayOfMind Blokke",
    "itemGroup.additions.items": "DayOfMind Items",
    "modmenu.additions.crowdin": "Help vertaal op Crowdin",
    "modmenu.additions.discord": "Sluit aan by die Discord",
    "modmenu.additions.github": "Bekyk op GitHub",
    "modmenu.additions.kofi": "Ondersteun ons op Ko-fi",
    "modmenu.additions.oxfatech": "OxFaTech Webtuiste",
    "tag.item.additions.stones": "Klippe",
    "tag.item.additions.stones.tooltip": "Alle klipvariante",
    "tooltip.additions.radius_mine.hammer_description": "Myn 'n %s area van klipagtige blokke.",
    "tooltip.additions.radius_mine.path_creation_description": "Gebruik om 'n pad te skep.",
    "tooltip.additions.radius_mine.shovel_description": "Myn 'n %s area van grondagtige blokke.",
    "tooltip.additions.radius_mine.sneak_description": "Sluip-gebruik om pad na grond te verander."
}