{
    "additions.midnightconfig.DayOfMind": "DayOfMind",
    "additions.midnightconfig.DetailedLogging": "Journalisation détaillée",
    "additions.midnightconfig.DetailedLogging.tooltip": "Active la journalisation détaillée de ce mod, comme le téléchargement des traductions. Il est probable que vous ne souhaitiez pas l'activer pour éviter de surcharger les logs.",
    "additions.midnightconfig.EnabledBlockVariants": "Activer les variantes de blocs",
    "additions.midnightconfig.EnabledBlockVariants.tooltip": "Active la possibilité de fabriquer plus de variantes de blocs (escaliers, dalles).",
    "additions.midnightconfig.EnabledInstruments": "Activer les instruments",
    "additions.midnightconfig.EnabledInstruments.tooltip": "Active la possibilité de fabriquer des instruments.",
    "additions.midnightconfig.EnabledLantern": "Activer les lanternes",
    "additions.midnightconfig.EnabledLantern.tooltip": "Active la possibilité de fabriquer plus de lanternes.",
    "additions.midnightconfig.EnabledRedstoneLantern": "Activer les lanternes à redstone",
    "additions.midnightconfig.EnabledRedstoneLantern.tooltip": "Active la possibilité de fabriquer des lanternes à redstone.",
    "additions.midnightconfig.EnabledShovelMixin": "Activer le basculement de chemin (pelle)",
    "additions.midnightconfig.EnabledShovelMixin.tooltip": "Permet de basculer entre un bloc d'herbe et un chemin de terre avec une pelle.",
    "additions.midnightconfig.EnabledTranslation": "Activer les traductions",
    "additions.midnightconfig.EnabledTranslation.tooltip": "Active le téléchargement automatique des traductions.",
    "additions.midnightconfig.EnabledTrapdoor": "Activer les trappes",
    "additions.midnightconfig.EnabledTrapdoor.tooltip": "Active la possibilité de fabriquer plus de trappes.",
    "additions.midnightconfig.TranslationUrl": "Source des traductions",
    "additions.midnightconfig.TranslationUrl.tooltip": "Sélectionnez la source des traductions.",
    "additions.midnightconfig.TranslationUrlCustom": "Source de traduction personnalisée",
    "additions.midnightconfig.TranslationUrlCustom.tooltip": "Entrez l'URL de la source de traduction personnalisée.",
    "additions.midnightconfig.aboutDayOfMind": "DayOfMind est un mod qui ajoute de nouveaux blocs, recettes et fonctionnalités. Avec des lanternes uniques, des variantes de blocs étendues et des fonctionnalités astucieuses comme le basculement entre les chemins d'herbe et de terre avec une pelle, DayOfMind offre des possibilités passionnantes pour vos aventures.",
    "additions.midnightconfig.category.about": "À propos de DayOfMind",
    "additions.midnightconfig.category.features": "Fonctionnalités",
    "additions.midnightconfig.enum.TranslationVersion.CROWDIN": "Crowdin",
    "additions.midnightconfig.enum.TranslationVersion.CUSTOM": "Personnalisée",
    "additions.midnightconfig.enum.TranslationVersion.OXFATECH": "OxFaTech",
    "additions.midnightconfig.features": "Les paramètres listés ici sont entièrement développés et peuvent être utilisés en toute sécurité.",
    "additions.midnightconfig.title": "Configuration de DayOfMind",
    "item.additions.big_diamond_shovel": "Grande pelle en diamant",
    "item.additions.big_gold_shovel": "Grande pelle en or",
    "item.additions.big_iron_shovel": "Grande pelle en fer",
    "item.additions.big_netherite_shovel": "Grande pelle en Netherite",
    "item.additions.big_stone_shovel": "Grande pelle en pierre",
    "item.additions.big_wood_shovel": "Grande pelle en bois",
    "item.additions.diamond_hammer": "Marteau en diamant",
    "item.additions.gold_hammer": "Marteau en or",
    "item.additions.iron_hammer": "Marteau en fer",
    "item.additions.netherite_hammer": "Marteau en Netherite",
    "item.additions.stone_hammer": "Marteau en pierre",
    "item.additions.wood_hammer": "Marteau en bois",
    "item.minecraft.amethyst_big_lantern": "Grande lanterne en améthyste",
    "item.minecraft.amethyst_big_redstone_lantern": "Grande lanterne à redstone en améthyste",
    "item.minecraft.amethyst_lantern": "Lanterne en améthyste",
    "item.minecraft.amethyst_redstone_lantern": "Lanterne à redstone en améthyste",
    "item.minecraft.amethyst_small_lantern": "Petite lanterne en améthyste",
    "item.minecraft.amethyst_small_redstone_lantern": "Petite lanterne à redstone en améthyste",
    "item.minecraft.amethyst_trapdoor": "Trappe en améthyste",
    "item.minecraft.andesite_trapdoor": "Trappe en andésite",
    "item.minecraft.basalt_trapdoor": "Trappe en basalte",
    "item.minecraft.blackstone_trapdoor": "Trappe en pierre noire",
    "item.minecraft.bricks_trapdoor": "Trappe en briques",
    "item.minecraft.chiseled_deepslate_trapdoor": "Trappe en ardoise des abîmes ciselée",
    "item.minecraft.chiseled_polished_blackstone_trapdoor": "Trappe en pierre noire polie ciselée",
    "item.minecraft.chiseled_quartz_trapdoor": "Trappe en quartz ciselé",
    "item.minecraft.chiseled_red_sandstone_trapdoor": "Trappe en grès rouge ciselé",
    "item.minecraft.chiseled_sandstone_trapdoor": "Trappe en grès ciselé",
    "item.minecraft.chiseled_stone_bricks_trapdoor": "Trappe en briques de pierre ciselées",
    "item.minecraft.chiseled_tuff_bricks_trapdoor": "Trappe en briques de tuf ciselées",
    "item.minecraft.chiseled_tuff_trapdoor": "Trappe en tuf ciselé",
    "item.minecraft.coarse_dirt_slab": "Dalle de terre stérile",
    "item.minecraft.coarse_dirt_stairs": "Escalier de terre stérile",
    "item.minecraft.cobbled_deepslate_trapdoor": "Trappe en pierres des abîmes",
    "item.minecraft.cobblestone_trapdoor": "Trappe en pierre",
    "item.minecraft.copper_big_lantern": "Grande lanterne en cuivre",
    "item.minecraft.copper_big_redstone_lantern": "Grande lanterne à redstone en cuivre",
    "item.minecraft.copper_lantern": "Lanterne en cuivre",
    "item.minecraft.copper_redstone_lantern": "Lanterne à redstone en cuivre",
    "item.minecraft.copper_small_lantern": "Petite lanterne en cuivre",
    "item.minecraft.copper_small_redstone_lantern": "Petite lanterne à redstone en cuivre",
    "item.minecraft.crying_obsidian_slab": "Dalle d'obsidienne pleureuse",
    "item.minecraft.crying_obsidian_stairs": "Escalier d'obsidienne pleureuse",
    "item.minecraft.dark_prismarine_trapdoor": "Trappe en prismarine sombre",
    "item.minecraft.deepslate_bricks_trapdoor": "Trappe en briques d'ardoise des abîmes",
    "item.minecraft.deepslate_tiles_trapdoor": "Trappe en tuiles d'ardoise des abîmes",
    "item.minecraft.deepslate_trapdoor": "Trappe en ardoise des abîmes",
    "item.minecraft.diamond_big_lantern": "Grande lanterne de diamant",
    "item.minecraft.diamond_big_redstone_lantern": "Grande lanterne à redstone de diamant",
    "item.minecraft.diamond_lantern": "Lanterne de diamant",
    "item.minecraft.diamond_redstone_lantern": "Lanterne à redstone de diamant",
    "item.minecraft.diamond_slab": "Dalle de diamant",
    "item.minecraft.diamond_small_lantern": "Petite lanterne de diamant",
    "item.minecraft.diamond_small_redstone_lantern": "Petite lanterne à redstone de diamant",
    "item.minecraft.diamond_stairs": "Escalier de diamant",
    "item.minecraft.diamond_trapdoor": "Trappe de diamant",
    "item.minecraft.diorite_trapdoor": "Trappe en diorite",
    "item.minecraft.dirt_path_slab": "Dalle de chemin de terre",
    "item.minecraft.dirt_path_stairs": "Escalier de chemin de terre",
    "item.minecraft.dirt_slab": "Dalle de terre",
    "item.minecraft.dirt_stairs": "Escalier de terre",
    "item.minecraft.emerald_big_lantern": "Grande lanterne d'émeraude",
    "item.minecraft.emerald_big_redstone_lantern": "Grande lanterne à redstone d'émeraude",
    "item.minecraft.emerald_lantern": "Lanterne d'émeraude",
    "item.minecraft.emerald_redstone_lantern": "Lanterne à redstone d'émeraude",
    "item.minecraft.emerald_small_lantern": "Petite lanterne d'émeraude",
    "item.minecraft.emerald_small_redstone_lantern": "Petite lanterne à redstone d'émeraude",
    "item.minecraft.emerald_trapdoor": "Trappe d'émeraude",
    "item.minecraft.end_stone_bricks_trapdoor": "Trappe en briques de pierre de l'End",
    "item.minecraft.end_stone_trapdoor": "Trappe en pierre de l'End",
    "item.minecraft.gold_big_lantern": "Grande lanterne d'or",
    "item.minecraft.gold_big_redstone_lantern": "Grande lanterne à redstone d'or",
    "item.minecraft.gold_lantern": "Lanterne d'or",
    "item.minecraft.gold_redstone_lantern": "Lanterne à redstone d'or",
    "item.minecraft.gold_slab": "Dalle d'or",
    "item.minecraft.gold_small_lantern": "Petite lanterne d'or",
    "item.minecraft.gold_small_redstone_lantern": "Petite lanterne à redstone d'or",
    "item.minecraft.gold_stairs": "Escalier d'or",
    "item.minecraft.gold_trapdoor": "Trappe d'or",
    "item.minecraft.granite_trapdoor": "Trappe en granite",
    "item.minecraft.grass_slab": "Dalle d'herbe",
    "item.minecraft.grass_stairs": "Escalier d'herbe",
    "item.minecraft.iron_big_lantern": "Grande lanterne de fer",
    "item.minecraft.iron_big_redstone_lantern": "Grande lanterne à redstone de fer",
    "item.minecraft.iron_redstone_lantern": "Lanterne à redstone de fer",
    "item.minecraft.iron_slab": "Dalle de fer",
    "item.minecraft.iron_small_lantern": "Petite lanterne de fer",
    "item.minecraft.iron_small_redstone_lantern": "Petite lanterne à redstone de fer",
    "item.minecraft.iron_stairs": "Escalier de fer",
    "item.minecraft.magma_slab": "Dalle de magma",
    "item.minecraft.magma_stairs": "Escalier de magma",
    "item.minecraft.moss_slab": "Dalle de mousse",
    "item.minecraft.moss_stairs": "Escalier de mousse",
    "item.minecraft.mossy_cobblestone_trapdoor": "Trappe en pierre moussue",
    "item.minecraft.mossy_stone_bricks_trapdoor": "Trappe en briques de pierre moussues",
    "item.minecraft.mud_bricks_trapdoor": "Trappe en briques de boue",
    "item.minecraft.mud_slab": "Dalle de boue",
    "item.minecraft.mud_stairs": "Escalier de boue",
    "item.minecraft.muddy_mangrove_roots_slab": "Dalle de racines de palétuvier boueuses",
    "item.minecraft.muddy_mangrove_roots_stairs": "Escalier de racines de palétuvier boueuses",
    "item.minecraft.mycelium_slab": "Dalle de mycélium",
    "item.minecraft.mycelium_stairs": "Escalier de mycélium",
    "item.minecraft.nether_bricks_trapdoor": "Trappe en briques du Nether",
    "item.minecraft.netherite_big_lantern": "Grande lanterne de Netherite",
    "item.minecraft.netherite_big_redstone_lantern": "Grande lanterne à redstone de Netherite",
    "item.minecraft.netherite_lantern": "Lanterne de Netherite",
    "item.minecraft.netherite_redstone_lantern": "Lanterne à redstone de Netherite",
    "item.minecraft.netherite_small_lantern": "Petite lanterne de Netherite",
    "item.minecraft.netherite_small_redstone_lantern": "Petite lanterne à redstone de Netherite",
    "item.minecraft.netherite_trapdoor": "Trappe de Netherite",
    "item.minecraft.netherrack_trapdoor": "Trappe en Netherrack",
    "item.minecraft.obsidian_slab": "Dalle d'obsidienne",
    "item.minecraft.obsidian_stairs": "Escalier d'obsidienne",
    "item.minecraft.podzol_slab": "Dalle de podzol",
    "item.minecraft.podzol_stairs": "Escalier de podzol",
    "item.minecraft.polished_andesite_trapdoor": "Trappe en andésite polie",
    "item.minecraft.polished_basalt_slab": "Dalle de basalte poli",
    "item.minecraft.polished_basalt_stairs": "Escalier de basalte poli",
    "item.minecraft.polished_basalt_trapdoor": "Trappe en basalte poli",
    "item.minecraft.polished_blackstone_bricks_trapdoor": "Trappe en briques de pierre noire polie",
    "item.minecraft.polished_blackstone_trapdoor": "Trappe en pierre noire polie",
    "item.minecraft.polished_deepslate_trapdoor": "Trappe en ardoise des abîmes polie",
    "item.minecraft.polished_diorite_trapdoor": "Trappe en diorite polie",
    "item.minecraft.polished_granite_trapdoor": "Trappe en granite poli",
    "item.minecraft.polished_tuff_trapdoor": "Trappe en tuf poli",
    "item.minecraft.prismarine_bricks_trapdoor": "Trappe en briques de prismarine",
    "item.minecraft.prismarine_trapdoor": "Trappe en prismarine",
    "item.minecraft.purpur_trapdoor": "Trappe en purpur",
    "item.minecraft.quartz_bricks_trapdoor": "Trappe en briques de quartz",
    "item.minecraft.quartz_trapdoor": "Trappe en quartz",
    "item.minecraft.red_nether_bricks_trapdoor": "Trappe en briques rouges du Nether",
    "item.minecraft.red_sandstone_trapdoor": "Trappe en grès rouge",
    "item.minecraft.redstone_chain": "Chaîne de redstone",
    "item.minecraft.rooted_dirt_slab": "Dalle de terre enracinée",
    "item.minecraft.rooted_dirt_stairs": "Escalier de terre enracinée",
    "item.minecraft.sandstone_trapdoor": "Trappe en grès",
    "item.minecraft.smooth_basalt_slab": "Dalle de basalte lisse",
    "item.minecraft.smooth_basalt_stairs": "Escalier de basalte lisse",
    "item.minecraft.smooth_basalt_trapdoor": "Trappe en basalte lisse",
    "item.minecraft.smooth_quartz_trapdoor": "Trappe en quartz lisse",
    "item.minecraft.smooth_red_sandstone_trapdoor": "Trappe en grès rouge lisse",
    "item.minecraft.smooth_sandstone_trapdoor": "Trappe en grès lisse",
    "item.minecraft.smooth_stone_trapdoor": "Trappe en roche lisse",
    "item.minecraft.stone_bricks_trapdoor": "Trappe en briques de pierre",
    "item.minecraft.stone_trapdoor": "Trappe en roche",
    "item.minecraft.tuff_bricks_trapdoor": "Trappe en briques de tuf",
    "item.minecraft.tuff_trapdoor": "Trappe en tuf",
    "itemGroup.additions.blocks": "Blocs de DayOfMind",
    "itemGroup.additions.items": "Objets de DayOfMind",
    "modmenu.additions.crowdin": "Aidez à traduire sur Crowdin",
    "modmenu.additions.discord": "Rejoignez le Discord",
    "modmenu.additions.github": "Voir sur GitHub",
    "modmenu.additions.kofi": "Soutenez-nous sur Ko-fi",
    "modmenu.additions.oxfatech": "Site web d'OxFaTech",
    "tag.item.additions.stones": "Roches",
    "tag.item.additions.stones.tooltip": "Toutes les variantes de roches",
    "tooltip.additions.radius_mine.hammer_description": "Mine une zone de %s de blocs de type roche.",
    "tooltip.additions.radius_mine.path_creation_description": "Utiliser pour créer un chemin.",
    "tooltip.additions.radius_mine.shovel_description": "Mine une zone de %s de blocs de type terre.",
    "tooltip.additions.radius_mine.sneak_description": "S'accroupir et utiliser pour retransformer en terre."
}